lowhaio_redirect.py
lowhaio_redirect-0.0.1.dist-info/LICENSE
lowhaio_redirect-0.0.1.dist-info/METADATA
lowhaio_redirect-0.0.1.dist-info/WHEEL
lowhaio_redirect-0.0.1.dist-info/top_level.txt
lowhaio_redirect-0.0.1.dist-info/RECORD
