Metadata-Version: 2.1
Name: lowhaio-redirect
Version: 0.0.1
Summary: Lowhaio wrapper that follows HTTP redirects
Home-page: https://github.com/michalc/lowhaio-redirect
Author: Michal Charemza
Author-email: michal@charemza.name
License: UNKNOWN
Platform: UNKNOWN
Classifier: Programming Language :: Python :: 3
Classifier: License :: OSI Approved :: MIT License
Classifier: Operating System :: OS Independent
Classifier: Framework :: AsyncIO
Requires-Python: >=3.6.3
